{"stock_symbol": "PRF2B", "trade_date": "2007-01-01", "prev_price": 7.0000, "open_price": 7.3000, "high_price": 7.3000, "low_price": 7.3000, "close_price": 7.3000, "total_volume": 1000, "fb_value": 0, "fs_value": 0, "nfb": 0, "value": 0, "num_txns": 0, "buy_vol": 0, "bid_qty": 0, "bid_price": 0.0000, "ask_qty": 0, "ask_price": 0.0000, "typical_price": 7.3000, "vwap": 0.0000, "to_ratio": 0.0000 }
{"stock_symbol": "PRF2B", "trade_date": "2014-11-03", "prev_price": 0.0000, "open_price": 1050.0000, "high_price": 1050.0000, "low_price": 1012.0000, "close_price": 1012.0000, "total_volume": 8690, "fb_value": -62520, "fs_value": 0, "nfb": 0, "value": 0, "num_txns": 0, "buy_vol": 0, "bid_qty": 0, "bid_price": 0.0000, "ask_qty": 0, "ask_price": 0.0000, "typical_price": 1024.6667, "vwap": 0.0000, "to_ratio": 0.0000 }
{"stock_symbol": "PRF2B", "trade_date": "2014-11-04", "prev_price": 1012.0000, "open_price": 1030.0000, "high_price": 1030.0000, "low_price": 1030.0000, "close_price": 1030.0000, "total_volume": 590, "fb_value": 0, "fs_value": 0, "nfb": 0, "value": 0, "num_txns": 0, "buy_vol": 0, "bid_qty": 0, "bid_price": 0.0000, "ask_qty": 0, "ask_price": 0.0000, "typical_price": 1030.0000, "vwap": 0.0000, "to_ratio": 0.0000 }
{"stock_symbol": "PRF2B", "trade_date": "2014-11-05", "prev_price": 1030.0000, "open_price": 1030.0000, "high_price": 1030.0000, "low_price": 1020.0000, "close_price": 1020.0000, "total_volume": 1100, "fb_value": 0, "fs_value": 0, "nfb": 0, "value": 0, "num_txns": 0, "buy_vol": 0, "bid_qty": 0, "bid_price": 0.0000, "ask_qty": 0, "ask_price": 0.0000, "typical_price": 1023.3333, "vwap": 0.0000, "to_ratio": 0.0000 }
{"stock_symbol": "PRF2B", "trade_date": "2014-11-06", "prev_price": 1020.0000, "open_price": 1025.0000, "high_price": 1025.0000, "low_price": 1025.0000, "close_price": 1025.0000, "total_volume": 40, "fb_value": 0, "fs_value": 0, "nfb": 0, "value": 0, "num_txns": 0, "buy_vol": 0, "bid_qty": 0, "bid_price": 0.0000, "ask_qty": 0, "ask_price": 0.0000, "typical_price": 1025.0000, "vwap": 0.0000, "to_ratio": 0.0000 }
{"stock_symbol": "PRF2B", "trade_date": "2014-11-07", "prev_price": 1025.0000, "open_price": 1020.0000, "high_price": 1020.0000, "low_price": 1020.0000, "close_price": 1020.0000, "total_volume": 2300, "fb_value": 0, "fs_value": 0, "nfb": 0, "value": 0, "num_txns": 0, "buy_vol": 0, "bid_qty": 0, "bid_price": 0.0000, "ask_qty": 0, "ask_price": 0.0000, "typical_price": 1020.0000, "vwap": 0.0000, "to_ratio": 0.0000 }
{"stock_symbol": "PRF2B", "trade_date": "2014-11-10", "prev_price": 1020.0000, "open_price": 1020.0000, "high_price": 1025.0000, "low_price": 1020.0000, "close_price": 1025.0000, "total_volume": 1820, "fb_value": 0, "fs_value": 0, "nfb": 0, "value": 0, "num_txns": 0, "buy_vol": 0, "bid_qty": 0, "bid_price": 0.0000, "ask_qty": 0, "ask_price": 0.0000, "typical_price": 1023.3333, "vwap": 0.0000, "to_ratio": 0.0000 }
{"stock_symbol": "PRF2B", "trade_date": "2014-11-11", "prev_price": 1025.0000, "open_price": 1020.0000, "high_price": 1020.0000, "low_price": 1015.0000, "close_price": 1015.0000, "total_volume": 6225, "fb_value": 0, "fs_value": 0, "nfb": 0, "value": 0, "num_txns": 0, "buy_vol": 0, "bid_qty": 0, "bid_price": 0.0000, "ask_qty": 0, "ask_price": 0.0000, "typical_price": 1016.6667, "vwap": 0.0000, "to_ratio": 0.0000 }
{"stock_symbol": "PRF2B", "trade_date": "2014-11-12", "prev_price": 1015.0000, "open_price": 1015.0000, "high_price": 1015.0000, "low_price": 1015.0000, "close_price": 1015.0000, "total_volume": 3055, "fb_value": 0, "fs_value": 0, "nfb": 0, "value": 0, "num_txns": 0, "buy_vol": 0, "bid_qty": 0, "bid_price": 0.0000, "ask_qty": 0, "ask_price": 0.0000, "typical_price": 1015.0000, "vwap": 0.0000, "to_ratio": 0.0000 }
{"stock_symbol": "PRF2B", "trade_date": "2014-11-13", "prev_price": 1015.0000, "open_price": 1030.0000, "high_price": 1030.0000, "low_price": 1030.0000, "close_price": 1030.0000, "total_volume": 30, "fb_value": 0, "fs_value": 0, "nfb": 0, "value": 0, "num_txns": 0, "buy_vol": 0, "bid_qty": 0, "bid_price": 0.0000, "ask_qty": 0, "ask_price": 0.0000, "typical_price": 1030.0000, "vwap": 0.0000, "to_ratio": 0.0000 }
{"stock_symbol": "PRF2B", "trade_date": "2014-11-14", "prev_price": 1030.0000, "open_price": 1020.0000, "high_price": 1020.0000, "low_price": 1020.0000, "close_price": 1020.0000, "total_volume": 1990, "fb_value": 0, "fs_value": 0, "nfb": 0, "value": 0, "num_txns": 0, "buy_vol": 0, "bid_qty": 0, "bid_price": 0.0000, "ask_qty": 0, "ask_price": 0.0000, "typical_price": 1020.0000, "vwap": 0.0000, "to_ratio": 0.0000 }
{"stock_symbol": "PRF2B", "trade_date": "2014-11-17", "prev_price": 1020.0000, "open_price": 1016.0000, "high_price": 1016.0000, "low_price": 1016.0000, "close_price": 1016.0000, "total_volume": 2180, "fb_value": 0, "fs_value": 0, "nfb": 0, "value": 0, "num_txns": 0, "buy_vol": 0, "bid_qty": 0, "bid_price": 0.0000, "ask_qty": 0, "ask_price": 0.0000, "typical_price": 1016.0000, "vwap": 0.0000, "to_ratio": 0.0000 }
{"stock_symbol": "PRF2B", "trade_date": "2014-11-18", "prev_price": 1016.0000, "open_price": 1017.0000, "high_price": 1029.0000, "low_price": 1016.0000, "close_price": 1029.0000, "total_volume": 1980, "fb_value": 0, "fs_value": 0, "nfb": 0, "value": 0, "num_txns": 0, "buy_vol": 0, "bid_qty": 0, "bid_price": 0.0000, "ask_qty": 0, "ask_price": 0.0000, "typical_price": 1024.6667, "vwap": 0.0000, "to_ratio": 0.0000 }
{"stock_symbol": "PRF2B", "trade_date": "2014-11-20", "prev_price": 1029.0000, "open_price": 1020.0000, "high_price": 1020.0000, "low_price": 1020.0000, "close_price": 1020.0000, "total_volume": 1000, "fb_value": 0, "fs_value": 0, "nfb": 0, "value": 0, "num_txns": 0, "buy_vol": 0, "bid_qty": 0, "bid_price": 0.0000, "ask_qty": 0, "ask_price": 0.0000, "typical_price": 1020.0000, "vwap": 0.0000, "to_ratio": 0.0000 }
{"stock_symbol": "PRF2B", "trade_date": "2014-11-21", "prev_price": 1020.0000, "open_price": 1030.0000, "high_price": 1030.0000, "low_price": 1030.0000, "close_price": 1030.0000, "total_volume": 2000, "fb_value": 0, "fs_value": 51500, "nfb": -51500, "value": 0, "num_txns": 0, "buy_vol": 0, "bid_qty": 0, "bid_price": 0.0000, "ask_qty": 0, "ask_price": 0.0000, "typical_price": 1030.0000, "vwap": 0.0000, "to_ratio": 0.0000 }
{"stock_symbol": "PRF2B", "trade_date": "2014-11-24", "prev_price": 1030.0000, "open_price": 1030.0000, "high_price": 1030.0000, "low_price": 1030.0000, "close_price": 1030.0000, "total_volume": 195, "fb_value": 0, "fs_value": 0, "nfb": 0, "value": 0, "num_txns": 0, "buy_vol": 0, "bid_qty": 0, "bid_price": 0.0000, "ask_qty": 0, "ask_price": 0.0000, "typical_price": 1030.0000, "vwap": 0.0000, "to_ratio": 0.0000 }
{"stock_symbol": "PRF2B", "trade_date": "2014-11-25", "prev_price": 1030.0000, "open_price": 1035.0000, "high_price": 1050.0000, "low_price": 1035.0000, "close_price": 1050.0000, "total_volume": 810, "fb_value": 0, "fs_value": 0, "nfb": 0, "value": 0, "num_txns": 0, "buy_vol": 0, "bid_qty": 0, "bid_price": 0.0000, "ask_qty": 0, "ask_price": 0.0000, "typical_price": 1045.0000, "vwap": 0.0000, "to_ratio": 0.0000 }
{"stock_symbol": "PRF2B", "trade_date": "2014-11-27", "prev_price": 1050.0000, "open_price": 1040.0000, "high_price": 1040.0000, "low_price": 1030.0000, "close_price": 1030.0000, "total_volume": 2260, "fb_value": 0, "fs_value": 0, "nfb": 0, "value": 0, "num_txns": 0, "buy_vol": 0, "bid_qty": 0, "bid_price": 0.0000, "ask_qty": 0, "ask_price": 0.0000, "typical_price": 1033.3333, "vwap": 0.0000, "to_ratio": 0.0000 }
{"stock_symbol": "PRF2B", "trade_date": "2014-11-28", "prev_price": 1030.0000, "open_price": 1045.0000, "high_price": 1045.0000, "low_price": 1045.0000, "close_price": 1045.0000, "total_volume": 350, "fb_value": 0, "fs_value": 0, "nfb": 0, "value": 0, "num_txns": 0, "buy_vol": 0, "bid_qty": 0, "bid_price": 0.0000, "ask_qty": 0, "ask_price": 0.0000, "typical_price": 1045.0000, "vwap": 0.0000, "to_ratio": 0.0000 }
{"stock_symbol": "PRF2B", "trade_date": "2014-12-02", "prev_price": 1045.0000, "open_price": 1040.0000, "high_price": 1040.0000, "low_price": 1040.0000, "close_price": 1040.0000, "total_volume": 250, "fb_value": 0, "fs_value": 0, "nfb": 0, "value": 0, "num_txns": 0, "buy_vol": 0, "bid_qty": 0, "bid_price": 0.0000, "ask_qty": 0, "ask_price": 0.0000, "typical_price": 1040.0000, "vwap": 0.0000, "to_ratio": 0.0000 }
{"stock_symbol": "PRF2B", "trade_date": "2014-12-03", "prev_price": 1040.0000, "open_price": 1030.0000, "high_price": 1050.0000, "low_price": 1018.0000, "close_price": 1050.0000, "total_volume": 525, "fb_value": 0, "fs_value": 0, "nfb": 0, "value": 0, "num_txns": 0, "buy_vol": 0, "bid_qty": 0, "bid_price": 0.0000, "ask_qty": 0, "ask_price": 0.0000, "typical_price": 1039.3333, "vwap": 0.0000, "to_ratio": 0.0000 }
{"stock_symbol": "PRF2B", "trade_date": "2014-12-05", "prev_price": 1050.0000, "open_price": 1040.0000, "high_price": 1040.0000, "low_price": 1040.0000, "close_price": 1040.0000, "total_volume": 100, "fb_value": 0, "fs_value": 0, "nfb": 0, "value": 0, "num_txns": 0, "buy_vol": 0, "bid_qty": 0, "bid_price": 0.0000, "ask_qty": 0, "ask_price": 0.0000, "typical_price": 1040.0000, "vwap": 0.0000, "to_ratio": 0.0000 }
{"stock_symbol": "PRF2B", "trade_date": "2014-12-09", "prev_price": 1040.0000, "open_price": 1040.0000, "high_price": 1040.0000, "low_price": 1040.0000, "close_price": 1040.0000, "total_volume": 1920, "fb_value": 0, "fs_value": 0, "nfb": 0, "value": 0, "num_txns": 0, "buy_vol": 0, "bid_qty": 0, "bid_price": 0.0000, "ask_qty": 0, "ask_price": 0.0000, "typical_price": 1040.0000, "vwap": 0.0000, "to_ratio": 0.0000 }
{"stock_symbol": "PRF2B", "trade_date": "2014-12-10", "prev_price": 1040.0000, "open_price": 1040.0000, "high_price": 1040.0000, "low_price": 1035.0000, "close_price": 1035.0000, "total_volume": 10020, "fb_value": 0, "fs_value": 0, "nfb": 0, "value": 0, "num_txns": 0, "buy_vol": 0, "bid_qty": 0, "bid_price": 0.0000, "ask_qty": 0, "ask_price": 0.0000, "typical_price": 1036.6667, "vwap": 0.0000, "to_ratio": 0.0000 }
{"stock_symbol": "PRF2B", "trade_date": "2014-12-15", "prev_price": 1035.0000, "open_price": 1030.0000, "high_price": 1030.0000, "low_price": 1030.0000, "close_price": 1030.0000, "total_volume": 1050, "fb_value": 0, "fs_value": 0, "nfb": 0, "value": 0, "num_txns": 0, "buy_vol": 0, "bid_qty": 0, "bid_price": 0.0000, "ask_qty": 0, "ask_price": 0.0000, "typical_price": 1030.0000, "vwap": 0.0000, "to_ratio": 0.0000 }
{"stock_symbol": "PRF2B", "trade_date": "2014-12-16", "prev_price": 1030.0000, "open_price": 1030.0000, "high_price": 1035.0000, "low_price": 1030.0000, "close_price": 1035.0000, "total_volume": 4000, "fb_value": 0, "fs_value": 0, "nfb": 0, "value": 0, "num_txns": 0, "buy_vol": 0, "bid_qty": 0, "bid_price": 0.0000, "ask_qty": 0, "ask_price": 0.0000, "typical_price": 1033.3333, "vwap": 0.0000, "to_ratio": 0.0000 }
{"stock_symbol": "PRF2B", "trade_date": "2014-12-17", "prev_price": 1035.0000, "open_price": 1035.0000, "high_price": 1035.0000, "low_price": 1030.0000, "close_price": 1030.0000, "total_volume": 12510, "fb_value": 0, "fs_value": 0, "nfb": 0, "value": 12887300, "num_txns": 5, "buy_vol": 400, "bid_qty": 0, "bid_price": 0.0000, "ask_qty": 0, "ask_price": 0.0000, "typical_price": 1031.6667, "vwap": 1030.1599, "to_ratio": 0.0000 }
{"stock_symbol": "PRF2B", "trade_date": "2014-12-18", "prev_price": 1030.0000, "open_price": 1030.0000, "high_price": 1030.0000, "low_price": 1030.0000, "close_price": 1030.0000, "total_volume": 20, "fb_value": 0, "fs_value": 0, "nfb": 0, "value": 0, "num_txns": 0, "buy_vol": 0, "bid_qty": 0, "bid_price": 0.0000, "ask_qty": 0, "ask_price": 0.0000, "typical_price": 1030.0000, "vwap": 0.0000, "to_ratio": 0.0000 }
{"stock_symbol": "PRF2B", "trade_date": "2015-01-05", "prev_price": 1030.0000, "open_price": 1040.0000, "high_price": 1040.0000, "low_price": 1040.0000, "close_price": 1040.0000, "total_volume": 500, "fb_value": 0, "fs_value": 0, "nfb": 0, "value": 520000, "num_txns": 1, "buy_vol": 500, "bid_qty": 0, "bid_price": 0.0000, "ask_qty": 0, "ask_price": 0.0000, "typical_price": 1040.0000, "vwap": 1040.0000, "to_ratio": 0.0000 }
{"stock_symbol": "PRF2B", "trade_date": "2015-01-06", "prev_price": 1040.0000, "open_price": 1040.0000, "high_price": 1040.0000, "low_price": 1040.0000, "close_price": 1040.0000, "total_volume": 1550, "fb_value": 0, "fs_value": 0, "nfb": 0, "value": 1612000, "num_txns": 3, "buy_vol": 1550, "bid_qty": 0, "bid_price": 0.0000, "ask_qty": 0, "ask_price": 0.0000, "typical_price": 1040.0000, "vwap": 1040.0000, "to_ratio": 0.0000 }
{"stock_symbol": "PRF2B", "trade_date": "2015-01-09", "prev_price": 1040.0000, "open_price": 1040.0000, "high_price": 1040.0000, "low_price": 1030.0000, "close_price": 1030.0000, "total_volume": 7000, "fb_value": 0, "fs_value": 0, "nfb": 0, "value": 7210140, "num_txns": 3, "buy_vol": 0, "bid_qty": 0, "bid_price": 0.0000, "ask_qty": 0, "ask_price": 0.0000, "typical_price": 1033.3333, "vwap": 1030.0200, "to_ratio": 0.0000 }
{"stock_symbol": "PRF2B", "trade_date": "2015-01-13", "prev_price": 1030.0000, "open_price": 1030.0000, "high_price": 1030.0000, "low_price": 1030.0000, "close_price": 1030.0000, "total_volume": 3700, "fb_value": 0, "fs_value": 0, "nfb": 0, "value": 3811000, "num_txns": 3, "buy_vol": 0, "bid_qty": 0, "bid_price": 0.0000, "ask_qty": 0, "ask_price": 0.0000, "typical_price": 1030.0000, "vwap": 1030.0000, "to_ratio": 0.0000 }
{"stock_symbol": "PRF2B", "trade_date": "2015-01-14", "prev_price": 1030.0000, "open_price": 1030.0000, "high_price": 1030.0000, "low_price": 1030.0000, "close_price": 1030.0000, "total_volume": 50, "fb_value": 0, "fs_value": 0, "nfb": 0, "value": 51500, "num_txns": 1, "buy_vol": 0, "bid_qty": 0, "bid_price": 0.0000, "ask_qty": 0, "ask_price": 0.0000, "typical_price": 1030.0000, "vwap": 1030.0000, "to_ratio": 0.0000 }
{"stock_symbol": "PRF2B", "trade_date": "2015-01-20", "prev_price": 1030.0000, "open_price": 1050.0000, "high_price": 1050.0000, "low_price": 1050.0000, "close_price": 1050.0000, "total_volume": 150, "fb_value": 0, "fs_value": 0, "nfb": 0, "value": 157500, "num_txns": 4, "buy_vol": 150, "bid_qty": 95, "bid_price": 1030.0000, "ask_qty": 970, "ask_price": 1045.0000, "typical_price": 1050.0000, "vwap": 1050.0000, "to_ratio": 0.0000 }
{"stock_symbol": "PRF2B", "trade_date": "2015-01-21", "prev_price": 1050.0000, "open_price": 1045.0000, "high_price": 1045.0000, "low_price": 1045.0000, "close_price": 1045.0000, "total_volume": 1900, "fb_value": 0, "fs_value": 0, "nfb": 0, "value": 1985500, "num_txns": 5, "buy_vol": 1900, "bid_qty": 100, "bid_price": 1030.0000, "ask_qty": 1220, "ask_price": 1045.0000, "typical_price": 1045.0000, "vwap": 1045.0000, "to_ratio": 0.0000 }
{"stock_symbol": "PRF2B", "trade_date": "2015-01-23", "prev_price": 1045.0000, "open_price": 1043.0000, "high_price": 1043.0000, "low_price": 1043.0000, "close_price": 1043.0000, "total_volume": 20, "fb_value": 0, "fs_value": 0, "nfb": 0, "value": 20860, "num_txns": 1, "buy_vol": 0, "bid_qty": 100, "bid_price": 1030.0000, "ask_qty": 500, "ask_price": 1043.0000, "typical_price": 1043.0000, "vwap": 1043.0000, "to_ratio": 0.0000 }
{"stock_symbol": "PRF2B", "trade_date": "2015-01-26", "prev_price": 1043.0000, "open_price": 1040.0000, "high_price": 1040.0000, "low_price": 1040.0000, "close_price": 1040.0000, "total_volume": 50, "fb_value": 0, "fs_value": 0, "nfb": 0, "value": 52000, "num_txns": 2, "buy_vol": 50, "bid_qty": 100, "bid_price": 1030.0000, "ask_qty": 5500, "ask_price": 1043.0000, "typical_price": 1040.0000, "vwap": 1040.0000, "to_ratio": 0.0000 }
{"stock_symbol": "PRF2B", "trade_date": "2015-01-27", "prev_price": 1040.0000, "open_price": 1040.0000, "high_price": 1040.0000, "low_price": 1040.0000, "close_price": 1040.0000, "total_volume": 25, "fb_value": 0, "fs_value": 0, "nfb": 0, "value": 26000, "num_txns": 1, "buy_vol": 25, "bid_qty": 100, "bid_price": 1030.0000, "ask_qty": 25, "ask_price": 1040.0000, "typical_price": 1040.0000, "vwap": 1040.0000, "to_ratio": 0.0000 }
{"stock_symbol": "PRF2B", "trade_date": "2015-01-28", "prev_price": 1040.0000, "open_price": 1030.0000, "high_price": 1030.0000, "low_price": 1030.0000, "close_price": 1030.0000, "total_volume": 200, "fb_value": 0, "fs_value": 0, "nfb": 0, "value": 206000, "num_txns": 3, "buy_vol": 100, "bid_qty": 340, "bid_price": 1030.0000, "ask_qty": 645, "ask_price": 1040.0000, "typical_price": 1030.0000, "vwap": 1030.0000, "to_ratio": 0.0000 }
{"stock_symbol": "PRF2B", "trade_date": "2015-01-29", "prev_price": 1030.0000, "open_price": 1030.0000, "high_price": 1030.0000, "low_price": 1025.0000, "close_price": 1030.0000, "total_volume": 950, "fb_value": 0, "fs_value": 0, "nfb": 0, "value": 977100, "num_txns": 9, "buy_vol": 250, "bid_qty": 50, "bid_price": 1020.0000, "ask_qty": 2000, "ask_price": 1040.0000, "typical_price": 1028.3333, "vwap": 1028.5263, "to_ratio": 0.0000 }
{"stock_symbol": "PRF2B", "trade_date": "2015-01-30", "prev_price": 1030.0000, "open_price": 1030.0000, "high_price": 1030.0000, "low_price": 1016.0000, "close_price": 1016.0000, "total_volume": 140, "fb_value": 0, "fs_value": 0, "nfb": 0, "value": 142800, "num_txns": 3, "buy_vol": 130, "bid_qty": 220, "bid_price": 1016.0000, "ask_qty": 2100, "ask_price": 1040.0000, "typical_price": 1020.6667, "vwap": 1020.0000, "to_ratio": 0.0000 }
{"stock_symbol": "PRF2B", "trade_date": "2015-02-02", "prev_price": 1016.0000, "open_price": 1018.0000, "high_price": 1040.0000, "low_price": 1018.0000, "close_price": 1040.0000, "total_volume": 550, "fb_value": 0, "fs_value": 405600, "nfb": -405600, "value": 569800, "num_txns": 3, "buy_vol": 500, "bid_qty": 500, "bid_price": 1022.0000, "ask_qty": 2110, "ask_price": 1040.0000, "typical_price": 1032.6667, "vwap": 1036.0000, "to_ratio": 0.0000 }
{"stock_symbol": "PRF2B", "trade_date": "2015-02-04", "prev_price": 1040.0000, "open_price": 1030.0000, "high_price": 1030.0000, "low_price": 1030.0000, "close_price": 1030.0000, "total_volume": 50, "fb_value": 0, "fs_value": 0, "nfb": 0, "value": 51500, "num_txns": 1, "buy_vol": 0, "bid_qty": 950, "bid_price": 1030.0000, "ask_qty": 7000, "ask_price": 1035.0000, "typical_price": 1030.0000, "vwap": 1030.0000, "to_ratio": 0.0000 }
{"stock_symbol": "PRF2B", "trade_date": "2015-02-05", "prev_price": 1030.0000, "open_price": 1030.0000, "high_price": 1035.0000, "low_price": 1030.0000, "close_price": 1035.0000, "total_volume": 4115, "fb_value": 0, "fs_value": 0, "nfb": 0, "value": 4245200, "num_txns": 7, "buy_vol": 1960, "bid_qty": 500, "bid_price": 1025.0000, "ask_qty": 5650, "ask_price": 1035.0000, "typical_price": 1033.3333, "vwap": 1031.6403, "to_ratio": 0.0000 }
{"stock_symbol": "PRF2B", "trade_date": "2015-02-09", "prev_price": 1035.0000, "open_price": 1025.0000, "high_price": 1033.0000, "low_price": 1025.0000, "close_price": 1033.0000, "total_volume": 750, "fb_value": 0, "fs_value": 0, "nfb": 0, "value": 769150, "num_txns": 6, "buy_vol": 170, "bid_qty": 500, "bid_price": 1022.0000, "ask_qty": 200, "ask_price": 1032.0000, "typical_price": 1030.3333, "vwap": 1025.5333, "to_ratio": 0.0000 }
{"stock_symbol": "PRF2B", "trade_date": "2015-02-11", "prev_price": 1033.0000, "open_price": 1030.0000, "high_price": 1030.0000, "low_price": 1020.0000, "close_price": 1020.0000, "total_volume": 1570, "fb_value": 0, "fs_value": 0, "nfb": 0, "value": 1604490, "num_txns": 14, "buy_vol": 505, "bid_qty": 615, "bid_price": 1020.0000, "ask_qty": 1100, "ask_price": 1030.0000, "typical_price": 1023.3333, "vwap": 1021.9682, "to_ratio": 0.0000 }
{"stock_symbol": "PRF2B", "trade_date": "2015-02-13", "prev_price": 1020.0000, "open_price": 1030.0000, "high_price": 1030.0000, "low_price": 1020.0000, "close_price": 1020.0000, "total_volume": 8665, "fb_value": 0, "fs_value": 0, "nfb": 0, "value": 8843800, "num_txns": 16, "buy_vol": 3465, "bid_qty": 250, "bid_price": 1018.0000, "ask_qty": 1745, "ask_price": 1020.0000, "typical_price": 1023.3333, "vwap": 1020.6347, "to_ratio": 0.0000 }
{"stock_symbol": "PRF2B", "trade_date": "2015-02-16", "prev_price": 1020.0000, "open_price": 1020.0000, "high_price": 1020.0000, "low_price": 1020.0000, "close_price": 1020.0000, "total_volume": 1745, "fb_value": 0, "fs_value": 0, "nfb": 0, "value": 1779900, "num_txns": 4, "buy_vol": 735, "bid_qty": 5000, "bid_price": 1020.0000, "ask_qty": 800, "ask_price": 1030.0000, "typical_price": 1020.0000, "vwap": 1020.0000, "to_ratio": 0.0000 }
{"stock_symbol": "PRF2B", "trade_date": "2015-02-17", "prev_price": 1020.0000, "open_price": 1020.0000, "high_price": 1030.0000, "low_price": 1020.0000, "close_price": 1030.0000, "total_volume": 4080, "fb_value": 0, "fs_value": 1642200, "nfb": -1642200, "value": 4184300, "num_txns": 7, "buy_vol": 2470, "bid_qty": 500, "bid_price": 1022.0000, "ask_qty": 4380, "ask_price": 1030.0000, "typical_price": 1026.6667, "vwap": 1025.5637, "to_ratio": 0.0000 }
{"stock_symbol": "PRF2B", "trade_date": "2015-02-18", "prev_price": 1030.0000, "open_price": 1030.0000, "high_price": 1030.0000, "low_price": 1030.0000, "close_price": 1030.0000, "total_volume": 300, "fb_value": 0, "fs_value": 0, "nfb": 0, "value": 309000, "num_txns": 1, "buy_vol": 300, "bid_qty": 1000, "bid_price": 1022.0000, "ask_qty": 4105, "ask_price": 1030.0000, "typical_price": 1030.0000, "vwap": 1030.0000, "to_ratio": 0.0000 }
{"stock_symbol": "PRF2B", "trade_date": "2015-02-20", "prev_price": 1030.0000, "open_price": 1030.0000, "high_price": 1030.0000, "low_price": 1030.0000, "close_price": 1030.0000, "total_volume": 890, "fb_value": 0, "fs_value": 0, "nfb": 0, "value": 916700, "num_txns": 1, "buy_vol": 890, "bid_qty": 300, "bid_price": 1026.0000, "ask_qty": 3190, "ask_price": 1030.0000, "typical_price": 1030.0000, "vwap": 1030.0000, "to_ratio": 0.0000 }
{"stock_symbol": "PRF2B", "trade_date": "2015-02-23", "prev_price": 1030.0000, "open_price": 1030.0000, "high_price": 1030.0000, "low_price": 1030.0000, "close_price": 1030.0000, "total_volume": 9320, "fb_value": 0, "fs_value": 0, "nfb": 0, "value": 9599600, "num_txns": 5, "buy_vol": 4190, "bid_qty": 1680, "bid_price": 1030.0000, "ask_qty": 200, "ask_price": 1033.0000, "typical_price": 1030.0000, "vwap": 1030.0000, "to_ratio": 0.0000 }
{"stock_symbol": "PRF2B", "trade_date": "2015-02-24", "prev_price": 1030.0000, "open_price": 1033.0000, "high_price": 1033.0000, "low_price": 1033.0000, "close_price": 1033.0000, "total_volume": 500, "fb_value": 0, "fs_value": 0, "nfb": 0, "value": 516500, "num_txns": 2, "buy_vol": 200, "bid_qty": 1680, "bid_price": 1030.0000, "ask_qty": 500, "ask_price": 1043.0000, "typical_price": 1033.0000, "vwap": 1033.0000, "to_ratio": 0.0000 }
{"stock_symbol": "PRF2B", "trade_date": "2015-02-27", "prev_price": 1033.0000, "open_price": 1033.0000, "high_price": 1033.0000, "low_price": 1033.0000, "close_price": 1033.0000, "total_volume": 50, "fb_value": 0, "fs_value": 0, "nfb": 0, "value": 51650, "num_txns": 3, "buy_vol": 50, "bid_qty": 300, "bid_price": 1031.0000, "ask_qty": 650, "ask_price": 1037.0000, "typical_price": 1033.0000, "vwap": 1033.0000, "to_ratio": 0.0000 }
{"stock_symbol": "PRF2B", "trade_date": "2015-03-03", "prev_price": 1033.0000, "open_price": 1034.0000, "high_price": 1034.0000, "low_price": 1034.0000, "close_price": 1034.0000, "total_volume": 600, "fb_value": 0, "fs_value": 0, "nfb": 0, "value": 620400, "num_txns": 1, "buy_vol": 0, "bid_qty": 1300, "bid_price": 1034.0000, "ask_qty": 50, "ask_price": 1037.0000, "typical_price": 1034.0000, "vwap": 1034.0000, "to_ratio": 0.0000 }
{"stock_symbol": "PRF2B", "trade_date": "2015-03-04", "prev_price": 1034.0000, "open_price": 1037.0000, "high_price": 1037.0000, "low_price": 1037.0000, "close_price": 1037.0000, "total_volume": 180, "fb_value": 0, "fs_value": 0, "nfb": 0, "value": 186660, "num_txns": 3, "buy_vol": 50, "bid_qty": 2940, "bid_price": 1037.0000, "ask_qty": 100, "ask_price": 1040.0000, "typical_price": 1037.0000, "vwap": 1037.0000, "to_ratio": 0.0000 }
{"stock_symbol": "PRF2B", "trade_date": "2015-03-05", "prev_price": 1037.0000, "open_price": 1041.0000, "high_price": 1060.0000, "low_price": 1041.0000, "close_price": 1060.0000, "total_volume": 1800, "fb_value": 0, "fs_value": 0, "nfb": 0, "value": 1892900, "num_txns": 5, "buy_vol": 1800, "bid_qty": 3575, "bid_price": 1040.0000, "ask_qty": 2470, "ask_price": 1060.0000, "typical_price": 1053.6667, "vwap": 1051.6111, "to_ratio": 0.0000 }
{"stock_symbol": "PRF2B", "trade_date": "2015-03-06", "prev_price": 1060.0000, "open_price": 1060.0000, "high_price": 1065.0000, "low_price": 1059.0000, "close_price": 1065.0000, "total_volume": 5860, "fb_value": 0, "fs_value": 0, "nfb": 0, "value": 6218380, "num_txns": 12, "buy_vol": 4610, "bid_qty": 5, "bid_price": 1060.0000, "ask_qty": 950, "ask_price": 1065.0000, "typical_price": 1063.0000, "vwap": 1061.1570, "to_ratio": 0.0000 }
{"stock_symbol": "PRF2B", "trade_date": "2015-03-09", "prev_price": 1065.0000, "open_price": 1065.0000, "high_price": 1065.0000, "low_price": 1065.0000, "close_price": 1065.0000, "total_volume": 2255, "fb_value": 0, "fs_value": 0, "nfb": 0, "value": 2401575, "num_txns": 11, "buy_vol": 1125, "bid_qty": 100, "bid_price": 1065.0000, "ask_qty": 30, "ask_price": 1070.0000, "typical_price": 1065.0000, "vwap": 1065.0000, "to_ratio": 0.0000 }
{"stock_symbol": "PRF2B", "trade_date": "2015-03-11", "prev_price": 1065.0000, "open_price": 1065.0000, "high_price": 1070.0000, "low_price": 1065.0000, "close_price": 1065.0000, "total_volume": 580, "fb_value": 0, "fs_value": 0, "nfb": 0, "value": 619200, "num_txns": 4, "buy_vol": 350, "bid_qty": 230, "bid_price": 1065.0000, "ask_qty": 1100, "ask_price": 1070.0000, "typical_price": 1066.6667, "vwap": 1067.5862, "to_ratio": 0.0000 }
{"stock_symbol": "PRF2B", "trade_date": "2015-03-12", "prev_price": 1065.0000, "open_price": 1070.0000, "high_price": 1075.0000, "low_price": 1070.0000, "close_price": 1075.0000, "total_volume": 4920, "fb_value": 0, "fs_value": 0, "nfb": 0, "value": 5283265, "num_txns": 9, "buy_vol": 4920, "bid_qty": 230, "bid_price": 1065.0000, "ask_qty": 1525, "ask_price": 1075.0000, "typical_price": 1073.3333, "vwap": 1073.8343, "to_ratio": 0.0000 }
{"stock_symbol": "PRF2B", "trade_date": "2015-03-13", "prev_price": 1075.0000, "open_price": 1075.0000, "high_price": 1075.0000, "low_price": 1065.0000, "close_price": 1065.0000, "total_volume": 3830, "fb_value": 0, "fs_value": 0, "nfb": 0, "value": 4097450, "num_txns": 4, "buy_vol": 1850, "bid_qty": 2730, "bid_price": 1065.0000, "ask_qty": 1000, "ask_price": 1075.0000, "typical_price": 1068.3333, "vwap": 1069.8303, "to_ratio": 0.0000 }
{"stock_symbol": "PRF2B", "trade_date": "2015-03-16", "prev_price": 1065.0000, "open_price": 1075.0000, "high_price": 1075.0000, "low_price": 1075.0000, "close_price": 1075.0000, "total_volume": 5795, "fb_value": 0, "fs_value": 0, "nfb": 0, "value": 6229625, "num_txns": 9, "buy_vol": 5795, "bid_qty": 330, "bid_price": 1065.0000, "ask_qty": 2505, "ask_price": 1075.0000, "typical_price": 1075.0000, "vwap": 1075.0000, "to_ratio": 0.0000 }
{"stock_symbol": "PRF2B", "trade_date": "2015-03-17", "prev_price": 1075.0000, "open_price": 1075.0000, "high_price": 1085.0000, "low_price": 1075.0000, "close_price": 1085.0000, "total_volume": 8280, "fb_value": 0, "fs_value": 0, "nfb": 0, "value": 8916750, "num_txns": 15, "buy_vol": 8280, "bid_qty": 3260, "bid_price": 1075.0000, "ask_qty": 150, "ask_price": 1085.0000, "typical_price": 1081.6667, "vwap": 1076.9022, "to_ratio": 0.0000 }
{"stock_symbol": "PRF2B", "trade_date": "2015-03-19", "prev_price": 1085.0000, "open_price": 1080.0000, "high_price": 1080.0000, "low_price": 1075.0000, "close_price": 1075.0000, "total_volume": 1000, "fb_value": 5400, "fs_value": 0, "nfb": 5400, "value": 1075525, "num_txns": 3, "buy_vol": 105, "bid_qty": 25, "bid_price": 1075.0000, "ask_qty": 245, "ask_price": 1080.0000, "typical_price": 1076.6667, "vwap": 1075.5250, "to_ratio": 0.0000 }
{"stock_symbol": "PRF2B", "trade_date": "2015-03-23", "prev_price": 1075.0000, "open_price": 1080.0000, "high_price": 1085.0000, "low_price": 1080.0000, "close_price": 1085.0000, "total_volume": 595, "fb_value": 0, "fs_value": 0, "nfb": 0, "value": 643100, "num_txns": 4, "buy_vol": 545, "bid_qty": 17405, "bid_price": 1080.0000, "ask_qty": 505, "ask_price": 1085.0000, "typical_price": 1083.3333, "vwap": 1080.8403, "to_ratio": 0.0000 }
{"stock_symbol": "PRF2B", "trade_date": "2015-03-24", "prev_price": 1085.0000, "open_price": 1085.0000, "high_price": 1085.0000, "low_price": 1080.0000, "close_price": 1080.0000, "total_volume": 8170, "fb_value": 0, "fs_value": 0, "nfb": 0, "value": 8830700, "num_txns": 10, "buy_vol": 1420, "bid_qty": 17405, "bid_price": 1080.0000, "ask_qty": 250, "ask_price": 1095.0000, "typical_price": 1081.6667, "vwap": 1080.8690, "to_ratio": 0.0000 }
{"stock_symbol": "PRF2B", "trade_date": "2015-03-25", "prev_price": 1080.0000, "open_price": 1085.0000, "high_price": 1085.0000, "low_price": 1080.0000, "close_price": 1080.0000, "total_volume": 10305, "fb_value": 0, "fs_value": 5400000, "nfb": -5400000, "value": 11152425, "num_txns": 8, "buy_vol": 4600, "bid_qty": 6085, "bid_price": 1080.0000, "ask_qty": 8550, "ask_price": 1085.0000, "typical_price": 1081.6667, "vwap": 1082.2344, "to_ratio": 0.0000 }
{"stock_symbol": "PRF2B", "trade_date": "2015-03-26", "prev_price": 1080.0000, "open_price": 1085.0000, "high_price": 1085.0000, "low_price": 1085.0000, "close_price": 1085.0000, "total_volume": 165, "fb_value": 0, "fs_value": 0, "nfb": 0, "value": 179025, "num_txns": 1, "buy_vol": 165, "bid_qty": 6155, "bid_price": 1080.0000, "ask_qty": 335, "ask_price": 1085.0000, "typical_price": 1085.0000, "vwap": 1085.0000, "to_ratio": 0.0000 }
{"stock_symbol": "PRF2B", "trade_date": "2015-03-27", "prev_price": 1085.0000, "open_price": 1085.0000, "high_price": 1100.0000, "low_price": 1085.0000, "close_price": 1100.0000, "total_volume": 835, "fb_value": 0, "fs_value": 0, "nfb": 0, "value": 913475, "num_txns": 3, "buy_vol": 835, "bid_qty": 6155, "bid_price": 1080.0000, "ask_qty": 3100, "ask_price": 1100.0000, "typical_price": 1095.0000, "vwap": 1093.9820, "to_ratio": 0.0000 }
{"stock_symbol": "PRF2B", "trade_date": "2015-03-31", "prev_price": 1100.0000, "open_price": 1080.0000, "high_price": 1080.0000, "low_price": 1080.0000, "close_price": 1080.0000, "total_volume": 5000, "fb_value": 0, "fs_value": 0, "nfb": 0, "value": 5400000, "num_txns": 2, "buy_vol": 0, "bid_qty": 5435, "bid_price": 1080.0000, "ask_qty": 150, "ask_price": 1100.0000, "typical_price": 1080.0000, "vwap": 1080.0000, "to_ratio": 0.0000 }
{"stock_symbol": "PRF2B", "trade_date": "2015-04-01", "prev_price": 1080.0000, "open_price": 1100.0000, "high_price": 1100.0000, "low_price": 1100.0000, "close_price": 1100.0000, "total_volume": 4200, "fb_value": 1859000, "fs_value": 3300000, "nfb": -1441000, "value": 4620000, "num_txns": 11, "buy_vol": 650, "bid_qty": 120, "bid_price": 1100.0000, "ask_qty": 5, "ask_price": 1108.0000, "typical_price": 1100.0000, "vwap": 1100.0000, "to_ratio": 0.0000 }
{"stock_symbol": "PRF2B", "trade_date": "2015-04-07", "prev_price": 1100.0000, "open_price": 1100.0000, "high_price": 1100.0000, "low_price": 1100.0000, "close_price": 1100.0000, "total_volume": 110, "fb_value": 0, "fs_value": 0, "nfb": 0, "value": 121000, "num_txns": 6, "buy_vol": 70, "bid_qty": 20, "bid_price": 1100.0000, "ask_qty": 100, "ask_price": 1106.0000, "typical_price": 1100.0000, "vwap": 1100.0000, "to_ratio": 0.0000 }
{"stock_symbol": "PRF2B", "trade_date": "2015-04-08", "prev_price": 1100.0000, "open_price": 1100.0000, "high_price": 1100.0000, "low_price": 1100.0000, "close_price": 1100.0000, "total_volume": 20, "fb_value": 0, "fs_value": 0, "nfb": 0, "value": 22000, "num_txns": 1, "buy_vol": 20, "bid_qty": 1500, "bid_price": 1085.0000, "ask_qty": 30, "ask_price": 1100.0000, "typical_price": 1100.0000, "vwap": 1100.0000, "to_ratio": 0.0000 }
{"stock_symbol": "PRF2B", "trade_date": "2015-04-10", "prev_price": 1100.0000, "open_price": 1100.0000, "high_price": 1105.0000, "low_price": 1100.0000, "close_price": 1105.0000, "total_volume": 400, "fb_value": 0, "fs_value": 132600, "nfb": -132600, "value": 441100, "num_txns": 3, "buy_vol": 400, "bid_qty": 580, "bid_price": 1100.0000, "ask_qty": 1880, "ask_price": 1105.0000, "typical_price": 1103.3333, "vwap": 1102.7500, "to_ratio": 0.0000 }
{"stock_symbol": "PRF2B", "trade_date": "2015-04-13", "prev_price": 1105.0000, "open_price": 1100.0000, "high_price": 1105.0000, "low_price": 1100.0000, "close_price": 1105.0000, "total_volume": 1045, "fb_value": 0, "fs_value": 806650, "nfb": -806650, "value": 1153150, "num_txns": 6, "buy_vol": 1000, "bid_qty": 975, "bid_price": 1100.0000, "ask_qty": 1150, "ask_price": 1105.0000, "typical_price": 1103.3333, "vwap": 1103.4928, "to_ratio": 0.0000 }
{"stock_symbol": "PRF2B", "trade_date": "2015-04-15", "prev_price": 1105.0000, "open_price": 1070.0000, "high_price": 1100.0000, "low_price": 1070.0000, "close_price": 1090.0000, "total_volume": 195, "fb_value": 0, "fs_value": 0, "nfb": 0, "value": 212200, "num_txns": 4, "buy_vol": 65, "bid_qty": 635, "bid_price": 1090.0000, "ask_qty": 2565, "ask_price": 1100.0000, "typical_price": 1086.6667, "vwap": 1088.2051, "to_ratio": 0.0000 }
{"stock_symbol": "PRF2B", "trade_date": "2015-04-16", "prev_price": 1090.0000, "open_price": 1090.0000, "high_price": 1090.0000, "low_price": 1070.0000, "close_price": 1070.0000, "total_volume": 625, "fb_value": 0, "fs_value": 0, "nfb": 0, "value": 678450, "num_txns": 6, "buy_vol": 0, "bid_qty": 2515, "bid_price": 1070.0000, "ask_qty": 15, "ask_price": 1095.0000, "typical_price": 1076.6667, "vwap": 1085.5200, "to_ratio": 0.0000 }
{"stock_symbol": "PRF2B", "trade_date": "2015-04-17", "prev_price": 1070.0000, "open_price": 1100.0000, "high_price": 1100.0000, "low_price": 1100.0000, "close_price": 1100.0000, "total_volume": 50, "fb_value": 0, "fs_value": 0, "nfb": 0, "value": 55000, "num_txns": 1, "buy_vol": 50, "bid_qty": 500, "bid_price": 1080.0000, "ask_qty": 2515, "ask_price": 1100.0000, "typical_price": 1100.0000, "vwap": 1100.0000, "to_ratio": 0.0000 }
{"stock_symbol": "PRF2B", "trade_date": "2015-04-20", "prev_price": 1100.0000, "open_price": 1098.0000, "high_price": 1100.0000, "low_price": 1098.0000, "close_price": 1100.0000, "total_volume": 2970, "fb_value": 0, "fs_value": 0, "nfb": 0, "value": 3266800, "num_txns": 9, "buy_vol": 2755, "bid_qty": 1950, "bid_price": 1100.0000, "ask_qty": 100, "ask_price": 1106.0000, "typical_price": 1099.3333, "vwap": 1099.9327, "to_ratio": 0.0000 }
{"stock_symbol": "PRF2B", "trade_date": "2015-04-21", "prev_price": 1100.0000, "open_price": 1100.0000, "high_price": 1100.0000, "low_price": 1100.0000, "close_price": 1100.0000, "total_volume": 900, "fb_value": 0, "fs_value": 0, "nfb": 0, "value": 990000, "num_txns": 3, "buy_vol": 0, "bid_qty": 1130, "bid_price": 1100.0000, "ask_qty": 300, "ask_price": 1105.0000, "typical_price": 1100.0000, "vwap": 1100.0000, "to_ratio": 0.0000 }
{"stock_symbol": "PRF2B", "trade_date": "2015-04-22", "prev_price": 1100.0000, "open_price": 1100.0000, "high_price": 1100.0000, "low_price": 1100.0000, "close_price": 1100.0000, "total_volume": 1130, "fb_value": 0, "fs_value": 1243000, "nfb": -1243000, "value": 1243000, "num_txns": 2, "buy_vol": 130, "bid_qty": 1955, "bid_price": 1080.0000, "ask_qty": 20, "ask_price": 1090.0000, "typical_price": 1100.0000, "vwap": 1100.0000, "to_ratio": 0.0000 }
{"stock_symbol": "PRF2B", "trade_date": "2015-04-23", "prev_price": 1100.0000, "open_price": 1095.0000, "high_price": 1095.0000, "low_price": 1095.0000, "close_price": 1095.0000, "total_volume": 1000, "fb_value": 0, "fs_value": 0, "nfb": 0, "value": 1095000, "num_txns": 1, "buy_vol": 0, "bid_qty": 1000, "bid_price": 1090.0000, "ask_qty": 100, "ask_price": 1105.0000, "typical_price": 1095.0000, "vwap": 1095.0000, "to_ratio": 0.0000 }
{"stock_symbol": "PRF2B", "trade_date": "2015-04-27", "prev_price": 1095.0000, "open_price": 1095.0000, "high_price": 1095.0000, "low_price": 1095.0000, "close_price": 1095.0000, "total_volume": 1000, "fb_value": 0, "fs_value": 0, "nfb": 0, "value": 1095000, "num_txns": 1, "buy_vol": 0, "bid_qty": 200, "bid_price": 1095.0000, "ask_qty": 100, "ask_price": 1115.0000, "typical_price": 1095.0000, "vwap": 1095.0000, "to_ratio": 0.0000 }
{"stock_symbol": "PRF2B", "trade_date": "2015-05-04", "prev_price": 1095.0000, "open_price": 1095.0000, "high_price": 1095.0000, "low_price": 1095.0000, "close_price": 1095.0000, "total_volume": 200, "fb_value": 0, "fs_value": 0, "nfb": 0, "value": 219000, "num_txns": 1, "buy_vol": 0, "bid_qty": 520, "bid_price": 1085.0000, "ask_qty": 520, "ask_price": 1095.0000, "typical_price": 1095.0000, "vwap": 1095.0000, "to_ratio": 0.0000 }
{"stock_symbol": "PRF2B", "trade_date": "2015-05-05", "prev_price": 1095.0000, "open_price": 1095.0000, "high_price": 1095.0000, "low_price": 1095.0000, "close_price": 1095.0000, "total_volume": 540, "fb_value": 0, "fs_value": 0, "nfb": 0, "value": 591300, "num_txns": 2, "buy_vol": 540, "bid_qty": 1000, "bid_price": 1090.0000, "ask_qty": 100, "ask_price": 1115.0000, "typical_price": 1095.0000, "vwap": 1095.0000, "to_ratio": 0.0000 }
{"stock_symbol": "PRF2B", "trade_date": "2015-05-07", "prev_price": 1095.0000, "open_price": 1100.0000, "high_price": 1100.0000, "low_price": 1100.0000, "close_price": 1100.0000, "total_volume": 150, "fb_value": 0, "fs_value": 0, "nfb": 0, "value": 165000, "num_txns": 4, "buy_vol": 45, "bid_qty": 10, "bid_price": 1082.0000, "ask_qty": 50, "ask_price": 1105.0000, "typical_price": 1100.0000, "vwap": 1100.0000, "to_ratio": 0.0000 }
{"stock_symbol": "PRF2B", "trade_date": "2015-05-12", "prev_price": 1100.0000, "open_price": 1095.0000, "high_price": 1095.0000, "low_price": 1095.0000, "close_price": 1095.0000, "total_volume": 120, "fb_value": 0, "fs_value": 0, "nfb": 0, "value": 131400, "num_txns": 1, "buy_vol": 0, "bid_qty": 880, "bid_price": 1095.0000, "ask_qty": 200, "ask_price": 1105.0000, "typical_price": 1095.0000, "vwap": 1095.0000, "to_ratio": 0.0000 }
{"stock_symbol": "PRF2B", "trade_date": "2015-05-13", "prev_price": 1095.0000, "open_price": 1095.0000, "high_price": 1095.0000, "low_price": 1085.0000, "close_price": 1085.0000, "total_volume": 1000, "fb_value": 0, "fs_value": 0, "nfb": 0, "value": 1093800, "num_txns": 3, "buy_vol": 0, "bid_qty": 1230, "bid_price": 1085.0000, "ask_qty": 150, "ask_price": 1105.0000, "typical_price": 1088.3333, "vwap": 1093.8000, "to_ratio": 0.0000 }
{"stock_symbol": "PRF2B", "trade_date": "2015-05-15", "prev_price": 1085.0000, "open_price": 1105.0000, "high_price": 1180.0000, "low_price": 1105.0000, "close_price": 1170.0000, "total_volume": 4295, "fb_value": 0, "fs_value": 162400, "nfb": -162400, "value": 4935100, "num_txns": 20, "buy_vol": 1165, "bid_qty": 10, "bid_price": 1096.0000, "ask_qty": 810, "ask_price": 1160.0000, "typical_price": 1151.6667, "vwap": 1149.0338, "to_ratio": 0.0000 }
{"stock_symbol": "PRF2B", "trade_date": "2015-05-20", "prev_price": 1170.0000, "open_price": 1096.0000, "high_price": 1096.0000, "low_price": 1095.0000, "close_price": 1095.0000, "total_volume": 2000, "fb_value": 0, "fs_value": 0, "nfb": 0, "value": 2190300, "num_txns": 3, "buy_vol": 0, "bid_qty": 10, "bid_price": 1097.0000, "ask_qty": 300, "ask_price": 1145.0000, "typical_price": 1095.3333, "vwap": 1095.1500, "to_ratio": 0.0000 }
{"stock_symbol": "PRF2B", "trade_date": "2015-05-27", "prev_price": 1095.0000, "open_price": 1095.0000, "high_price": 1095.0000, "low_price": 1088.0000, "close_price": 1088.0000, "total_volume": 4310, "fb_value": 0, "fs_value": 0, "nfb": 0, "value": 4713180, "num_txns": 5, "buy_vol": 100, "bid_qty": 150, "bid_price": 1089.0000, "ask_qty": 300, "ask_price": 1091.0000, "typical_price": 1090.3333, "vwap": 1093.5452, "to_ratio": 0.0000 }
{"stock_symbol": "PRF2B", "trade_date": "2015-05-28", "prev_price": 1088.0000, "open_price": 1085.0000, "high_price": 1090.0000, "low_price": 1085.0000, "close_price": 1090.0000, "total_volume": 870, "fb_value": 0, "fs_value": 0, "nfb": 0, "value": 947950, "num_txns": 3, "buy_vol": 0, "bid_qty": 80, "bid_price": 1091.0000, "ask_qty": 70, "ask_price": 1140.0000, "typical_price": 1088.3333, "vwap": 1089.5977, "to_ratio": 0.0000 }
{"stock_symbol": "PRF2B", "trade_date": "2015-06-02", "prev_price": 1090.0000, "open_price": 1091.0000, "high_price": 1091.0000, "low_price": 1091.0000, "close_price": 1091.0000, "total_volume": 2270, "fb_value": 0, "fs_value": 0, "nfb": 0, "value": 2476570, "num_txns": 14, "buy_vol": 1605, "bid_qty": 2100, "bid_price": 1090.0000, "ask_qty": 795, "ask_price": 1091.0000, "typical_price": 1091.0000, "vwap": 1091.0000, "to_ratio": 0.0000 }
{"stock_symbol": "PRF2B", "trade_date": "2015-06-09", "prev_price": 1091.0000, "open_price": 1092.0000, "high_price": 1092.0000, "low_price": 1091.0000, "close_price": 1091.0000, "total_volume": 2000, "fb_value": 0, "fs_value": 0, "nfb": 0, "value": 2182020, "num_txns": 3, "buy_vol": 0, "bid_qty": 5, "bid_price": 1092.0000, "ask_qty": 300, "ask_price": 1140.0000, "typical_price": 1091.3333, "vwap": 1091.0100, "to_ratio": 0.0000 }
{"stock_symbol": "PRF2B", "trade_date": "2015-06-25", "prev_price": 1091.0000, "open_price": 1149.0000, "high_price": 1149.0000, "low_price": 1148.0000, "close_price": 1149.0000, "total_volume": 8045, "fb_value": 0, "fs_value": 1149000, "nfb": -1149000, "value": 9243660, "num_txns": 17, "buy_vol": 4720, "bid_qty": 2365, "bid_price": 1149.0000, "ask_qty": 7000, "ask_price": 1150.0000, "typical_price": 1148.6667, "vwap": 1148.9944, "to_ratio": 0.0000 }
{"stock_symbol": "PRF2B", "trade_date": "2015-06-29", "prev_price": 1149.0000, "open_price": 1148.0000, "high_price": 1149.0000, "low_price": 1148.0000, "close_price": 1149.0000, "total_volume": 2365, "fb_value": 0, "fs_value": 0, "nfb": 0, "value": 2715065, "num_txns": 5, "buy_vol": 1265, "bid_qty": 100, "bid_price": 1101.0000, "ask_qty": 7155, "ask_price": 1149.0000, "typical_price": 1148.6667, "vwap": 1148.0190, "to_ratio": 0.0000 }
{"stock_symbol": "PRF2B", "trade_date": "2015-07-01", "prev_price": 1149.0000, "open_price": 1149.0000, "high_price": 1149.0000, "low_price": 1149.0000, "close_price": 1149.0000, "total_volume": 2600, "fb_value": 0, "fs_value": 0, "nfb": 0, "value": 2987400, "num_txns": 1, "buy_vol": 2600, "bid_qty": 100, "bid_price": 1103.0000, "ask_qty": 1000, "ask_price": 1148.0000, "typical_price": 1149.0000, "vwap": 1149.0000, "to_ratio": 0.0000 }
{"stock_symbol": "PRF2B", "trade_date": "2015-07-07", "prev_price": 1149.0000, "open_price": 1148.0000, "high_price": 1148.0000, "low_price": 1148.0000, "close_price": 1148.0000, "total_volume": 30, "fb_value": 0, "fs_value": 0, "nfb": 0, "value": 34440, "num_txns": 2, "buy_vol": 30, "bid_qty": 230, "bid_price": 1102.0000, "ask_qty": 2370, "ask_price": 1148.0000, "typical_price": 1148.0000, "vwap": 1148.0000, "to_ratio": 0.0000 }
{"stock_symbol": "PRF2B", "trade_date": "2015-07-08", "prev_price": 1148.0000, "open_price": 1148.0000, "high_price": 1148.0000, "low_price": 1148.0000, "close_price": 1148.0000, "total_volume": 25, "fb_value": 0, "fs_value": 0, "nfb": 0, "value": 28700, "num_txns": 1, "buy_vol": 0, "bid_qty": 110, "bid_price": 1102.0000, "ask_qty": 1480, "ask_price": 1148.0000, "typical_price": 1148.0000, "vwap": 1148.0000, "to_ratio": 0.0000 }
{"stock_symbol": "PRF2B", "trade_date": "2015-07-13", "prev_price": 1148.0000, "open_price": 1148.0000, "high_price": 1149.0000, "low_price": 1148.0000, "close_price": 1149.0000, "total_volume": 4340, "fb_value": 0, "fs_value": 0, "nfb": 0, "value": 4985235, "num_txns": 5, "buy_vol": 4340, "bid_qty": 180, "bid_price": 1110.0000, "ask_qty": 1490, "ask_price": 1149.0000, "typical_price": 1148.6667, "vwap": 1148.6717, "to_ratio": 0.0000 }
{"stock_symbol": "PRF2B", "trade_date": "2015-07-15", "prev_price": 1149.0000, "open_price": 1149.0000, "high_price": 1149.0000, "low_price": 1149.0000, "close_price": 1149.0000, "total_volume": 90, "fb_value": 0, "fs_value": 0, "nfb": 0, "value": 103410, "num_txns": 2, "buy_vol": 90, "bid_qty": 3625, "bid_price": 1100.0000, "ask_qty": 1435, "ask_price": 1149.0000, "typical_price": 1149.0000, "vwap": 1149.0000, "to_ratio": 0.0000 }
{"stock_symbol": "PRF2B", "trade_date": "2015-07-20", "prev_price": 1149.0000, "open_price": 1148.0000, "high_price": 1148.0000, "low_price": 1148.0000, "close_price": 1148.0000, "total_volume": 4560, "fb_value": 0, "fs_value": 0, "nfb": 0, "value": 5234880, "num_txns": 10, "buy_vol": 1000, "bid_qty": 0, "bid_price": 0.0000, "ask_qty": 0, "ask_price": 0.0000, "typical_price": 1148.0000, "vwap": 1148.0000, "to_ratio": 0.0000 }
{"stock_symbol": "PRF2B", "trade_date": "2015-07-21", "prev_price": 1148.0000, "open_price": 1148.0000, "high_price": 1148.0000, "low_price": 1148.0000, "close_price": 1148.0000, "total_volume": 1800, "fb_value": 0, "fs_value": 0, "nfb": 0, "value": 2066400, "num_txns": 3, "buy_vol": 0, "bid_qty": 1540, "bid_price": 1148.0000, "ask_qty": 1435, "ask_price": 1149.0000, "typical_price": 1148.0000, "vwap": 1148.0000, "to_ratio": 0.0000 }
{"stock_symbol": "PRF2B", "trade_date": "2015-07-22", "prev_price": 1148.0000, "open_price": 1148.0000, "high_price": 1148.0000, "low_price": 1148.0000, "close_price": 1148.0000, "total_volume": 400, "fb_value": 0, "fs_value": 0, "nfb": 0, "value": 459200, "num_txns": 1, "buy_vol": 0, "bid_qty": 3840, "bid_price": 1148.0000, "ask_qty": 1435, "ask_price": 1149.0000, "typical_price": 1148.0000, "vwap": 1148.0000, "to_ratio": 0.0000 }
{"stock_symbol": "PRF2B", "trade_date": "2015-07-23", "prev_price": 1148.0000, "open_price": 1148.0000, "high_price": 1148.0000, "low_price": 1148.0000, "close_price": 1148.0000, "total_volume": 5320, "fb_value": 0, "fs_value": 0, "nfb": 0, "value": 6107360, "num_txns": 4, "buy_vol": 1480, "bid_qty": 3520, "bid_price": 1148.0000, "ask_qty": 1440, "ask_price": 1149.0000, "typical_price": 1148.0000, "vwap": 1148.0000, "to_ratio": 0.0000 }
{"stock_symbol": "PRF2B", "trade_date": "2015-07-24", "prev_price": 1148.0000, "open_price": 1148.0000, "high_price": 1148.0000, "low_price": 1148.0000, "close_price": 1148.0000, "total_volume": 3435, "fb_value": 0, "fs_value": 0, "nfb": 0, "value": 3943380, "num_txns": 4, "buy_vol": 0, "bid_qty": 85, "bid_price": 1148.0000, "ask_qty": 100, "ask_price": 1152.0000, "typical_price": 1148.0000, "vwap": 1148.0000, "to_ratio": 0.0000 }
{"stock_symbol": "PRF2B", "trade_date": "2015-07-28", "prev_price": 1102.0000, "open_price": 1101.0000, "high_price": 1101.0000, "low_price": 1100.0000, "close_price": 1100.0000, "total_volume": 2900, "fb_value": 0, "fs_value": 0, "nfb": 0, "value": 3190170, "num_txns": 6, "buy_vol": 0, "bid_qty": 3195, "bid_price": 1100.0000, "ask_qty": 100, "ask_price": 1148.0000, "typical_price": 1100.3333, "vwap": 1100.0586, "to_ratio": 0.0000 }
{"stock_symbol": "PRF2B", "trade_date": "2015-07-29", "prev_price": 1100.0000, "open_price": 1101.0000, "high_price": 1105.0000, "low_price": 1100.0000, "close_price": 1105.0000, "total_volume": 1040, "fb_value": 0, "fs_value": 0, "nfb": 0, "value": 1144115, "num_txns": 6, "buy_vol": 95, "bid_qty": 210, "bid_price": 1095.0000, "ask_qty": 70, "ask_price": 1100.0000, "typical_price": 1103.3333, "vwap": 1100.1106, "to_ratio": 0.0000 }
{"stock_symbol": "PRF2B", "trade_date": "2015-07-31", "prev_price": 1105.0000, "open_price": 1105.0000, "high_price": 1105.0000, "low_price": 1105.0000, "close_price": 1105.0000, "total_volume": 100, "fb_value": 0, "fs_value": 0, "nfb": 0, "value": 110500, "num_txns": 2, "buy_vol": 100, "bid_qty": 100, "bid_price": 1100.0000, "ask_qty": 90, "ask_price": 1143.0000, "typical_price": 1105.0000, "vwap": 1105.0000, "to_ratio": 0.0000 }
{"stock_symbol": "PRF2B", "trade_date": "2015-08-04", "prev_price": 1105.0000, "open_price": 1105.0000, "high_price": 1105.0000, "low_price": 1091.0000, "close_price": 1091.0000, "total_volume": 4910, "fb_value": 0, "fs_value": 1092780, "nfb": -1092780, "value": 5358940, "num_txns": 11, "buy_vol": 20, "bid_qty": 210, "bid_price": 1095.0000, "ask_qty": 195, "ask_price": 1105.0000, "typical_price": 1095.6667, "vwap": 1091.4338, "to_ratio": 0.0000 }
{"stock_symbol": "PRF2B", "trade_date": "2015-08-05", "prev_price": 1091.0000, "open_price": 1091.0000, "high_price": 1091.0000, "low_price": 1091.0000, "close_price": 1091.0000, "total_volume": 1670, "fb_value": 0, "fs_value": 1745600, "nfb": -1745600, "value": 1821970, "num_txns": 2, "buy_vol": 0, "bid_qty": 0, "bid_price": 0.0000, "ask_qty": 0, "ask_price": 0.0000, "typical_price": 1091.0000, "vwap": 1091.0000, "to_ratio": 0.0000 }
{"stock_symbol": "PRF2B", "trade_date": "2015-08-06", "prev_price": 1091.0000, "open_price": 1090.0000, "high_price": 1090.0000, "low_price": 1090.0000, "close_price": 1090.0000, "total_volume": 80, "fb_value": 0, "fs_value": 0, "nfb": 0, "value": 87200, "num_txns": 1, "buy_vol": 80, "bid_qty": 200, "bid_price": 1085.0000, "ask_qty": 90, "ask_price": 1143.0000, "typical_price": 1090.0000, "vwap": 1090.0000, "to_ratio": 0.0000 }
{"stock_symbol": "PRF2B", "trade_date": "2015-08-07", "prev_price": 1090.0000, "open_price": 1085.0000, "high_price": 1085.0000, "low_price": 1085.0000, "close_price": 1085.0000, "total_volume": 20, "fb_value": 0, "fs_value": 0, "nfb": 0, "value": 21700, "num_txns": 1, "buy_vol": 20, "bid_qty": 1955, "bid_price": 1080.0000, "ask_qty": 5, "ask_price": 1090.0000, "typical_price": 1085.0000, "vwap": 1085.0000, "to_ratio": 0.0000 }
{"stock_symbol": "PRF2B", "trade_date": "2015-08-10", "prev_price": 1085.0000, "open_price": 1081.0000, "high_price": 1081.0000, "low_price": 1081.0000, "close_price": 1081.0000, "total_volume": 50, "fb_value": 0, "fs_value": 0, "nfb": 0, "value": 54050, "num_txns": 1, "buy_vol": 0, "bid_qty": 50, "bid_price": 1081.0000, "ask_qty": 1410, "ask_price": 1085.0000, "typical_price": 1081.0000, "vwap": 1081.0000, "to_ratio": 0.0000 }
{"stock_symbol": "PRF2B", "trade_date": "2015-08-11", "prev_price": 1081.0000, "open_price": 1080.0000, "high_price": 1080.0000, "low_price": 1080.0000, "close_price": 1080.0000, "total_volume": 90, "fb_value": 0, "fs_value": 0, "nfb": 0, "value": 97200, "num_txns": 1, "buy_vol": 0, "bid_qty": 100, "bid_price": 1081.0000, "ask_qty": 1410, "ask_price": 1085.0000, "typical_price": 1080.0000, "vwap": 1080.0000, "to_ratio": 0.0000 }
{"stock_symbol": "PRF2B", "trade_date": "2015-08-12", "prev_price": 1080.0000, "open_price": 1080.0000, "high_price": 1080.0000, "low_price": 1080.0000, "close_price": 1080.0000, "total_volume": 5, "fb_value": 0, "fs_value": 0, "nfb": 0, "value": 5400, "num_txns": 1, "buy_vol": 0, "bid_qty": 1860, "bid_price": 1080.0000, "ask_qty": 1410, "ask_price": 1085.0000, "typical_price": 1080.0000, "vwap": 1080.0000, "to_ratio": 0.0000 }
{"stock_symbol": "PRF2B", "trade_date": "2015-08-13", "prev_price": 1080.0000, "open_price": 1080.0000, "high_price": 1080.0000, "low_price": 1080.0000, "close_price": 1080.0000, "total_volume": 870, "fb_value": 0, "fs_value": 0, "nfb": 0, "value": 939600, "num_txns": 1, "buy_vol": 0, "bid_qty": 990, "bid_price": 1080.0000, "ask_qty": 1410, "ask_price": 1085.0000, "typical_price": 1080.0000, "vwap": 1080.0000, "to_ratio": 0.0000 }
{"stock_symbol": "PRF2B", "trade_date": "2015-08-17", "prev_price": 1080.0000, "open_price": 1080.0000, "high_price": 1080.0000, "low_price": 1080.0000, "close_price": 1080.0000, "total_volume": 990, "fb_value": 0, "fs_value": 0, "nfb": 0, "value": 1069200, "num_txns": 2, "buy_vol": 0, "bid_qty": 100, "bid_price": 1066.0000, "ask_qty": 20, "ask_price": 1080.0000, "typical_price": 1080.0000, "vwap": 1080.0000, "to_ratio": 0.0000 }
{"stock_symbol": "PRF2B", "trade_date": "2015-08-20", "prev_price": 1080.0000, "open_price": 1080.0000, "high_price": 1085.0000, "low_price": 1080.0000, "close_price": 1085.0000, "total_volume": 2615, "fb_value": 0, "fs_value": 0, "nfb": 0, "value": 2834890, "num_txns": 4, "buy_vol": 2615, "bid_qty": 6905, "bid_price": 1085.0000, "ask_qty": 3000, "ask_price": 1100.0000, "typical_price": 1083.3333, "vwap": 1084.0880, "to_ratio": 0.0000 }
{"stock_symbol": "PRF2B", "trade_date": "2015-08-24", "prev_price": 1085.0000, "open_price": 1100.0000, "high_price": 1100.0000, "low_price": 1100.0000, "close_price": 1100.0000, "total_volume": 285, "fb_value": 313500, "fs_value": 0, "nfb": 313500, "value": 313500, "num_txns": 1, "buy_vol": 285, "bid_qty": 2890, "bid_price": 1065.0000, "ask_qty": 200, "ask_price": 1085.0000, "typical_price": 1100.0000, "vwap": 1100.0000, "to_ratio": 0.0000 }
{"stock_symbol": "PRF2B", "trade_date": "2015-08-25", "prev_price": 1100.0000, "open_price": 1065.0000, "high_price": 1085.0000, "low_price": 1065.0000, "close_price": 1085.0000, "total_volume": 300, "fb_value": 43400, "fs_value": 0, "nfb": 43400, "value": 320300, "num_txns": 2, "buy_vol": 40, "bid_qty": 2645, "bid_price": 1065.0000, "ask_qty": 160, "ask_price": 1085.0000, "typical_price": 1078.3333, "vwap": 1067.6667, "to_ratio": 0.0000 }
{"stock_symbol": "PRF2B", "trade_date": "2015-08-26", "prev_price": 1085.0000, "open_price": 1075.0000, "high_price": 1075.0000, "low_price": 1075.0000, "close_price": 1075.0000, "total_volume": 110, "fb_value": 0, "fs_value": 0, "nfb": 0, "value": 118250, "num_txns": 2, "buy_vol": 0, "bid_qty": 5, "bid_price": 1070.0000, "ask_qty": 160, "ask_price": 1085.0000, "typical_price": 1075.0000, "vwap": 1075.0000, "to_ratio": 0.0000 }
{"stock_symbol": "PRF2B", "trade_date": "2015-08-27", "prev_price": 1075.0000, "open_price": 1085.0000, "high_price": 1085.0000, "low_price": 1085.0000, "close_price": 1085.0000, "total_volume": 5, "fb_value": 0, "fs_value": 0, "nfb": 0, "value": 5425, "num_txns": 1, "buy_vol": 5, "bid_qty": 500, "bid_price": 1070.0000, "ask_qty": 110, "ask_price": 1140.0000, "typical_price": 1085.0000, "vwap": 1085.0000, "to_ratio": 0.0000 }
{"stock_symbol": "PRF2B", "trade_date": "2015-08-28", "prev_price": 1085.0000, "open_price": 1140.0000, "high_price": 1140.0000, "low_price": 1140.0000, "close_price": 1140.0000, "total_volume": 10, "fb_value": 0, "fs_value": 0, "nfb": 0, "value": 11400, "num_txns": 1, "buy_vol": 10, "bid_qty": 3000, "bid_price": 1085.0000, "ask_qty": 100, "ask_price": 1139.0000, "typical_price": 1140.0000, "vwap": 1140.0000, "to_ratio": 0.0000 }
{"stock_symbol": "PRF2B", "trade_date": "2015-09-10", "prev_price": 1140.0000, "open_price": 1100.0000, "high_price": 1100.0000, "low_price": 1100.0000, "close_price": 1100.0000, "total_volume": 10, "fb_value": 0, "fs_value": 0, "nfb": 0, "value": 11000, "num_txns": 1, "buy_vol": 0, "bid_qty": 10, "bid_price": 1070.0000, "ask_qty": 190, "ask_price": 1100.0000, "typical_price": 1100.0000, "vwap": 1100.0000, "to_ratio": 0.0000 }
{"stock_symbol": "PRF2B", "trade_date": "2015-09-11", "prev_price": 1100.0000, "open_price": 1100.0000, "high_price": 1100.0000, "low_price": 1100.0000, "close_price": 1100.0000, "total_volume": 190, "fb_value": 0, "fs_value": 0, "nfb": 0, "value": 209000, "num_txns": 1, "buy_vol": 190, "bid_qty": 110, "bid_price": 1100.0000, "ask_qty": 715, "ask_price": 1120.0000, "typical_price": 1100.0000, "vwap": 1100.0000, "to_ratio": 0.0000 }
{"stock_symbol": "PRF2B", "trade_date": "2015-09-15", "prev_price": 1100.0000, "open_price": 1100.0000, "high_price": 1100.0000, "low_price": 1100.0000, "close_price": 1100.0000, "total_volume": 500, "fb_value": 0, "fs_value": 0, "nfb": 0, "value": 550000, "num_txns": 1, "buy_vol": 0, "bid_qty": 110, "bid_price": 1100.0000, "ask_qty": 715, "ask_price": 1120.0000, "typical_price": 1100.0000, "vwap": 1100.0000, "to_ratio": 0.0000 }
{"stock_symbol": "PRF2B", "trade_date": "2015-09-16", "prev_price": 1100.0000, "open_price": 1100.0000, "high_price": 1100.0000, "low_price": 1090.0000, "close_price": 1090.0000, "total_volume": 500, "fb_value": 0, "fs_value": 0, "nfb": 0, "value": 546100, "num_txns": 2, "buy_vol": 0, "bid_qty": 110, "bid_price": 1090.0000, "ask_qty": 715, "ask_price": 1120.0000, "typical_price": 1093.3333, "vwap": 1092.2000, "to_ratio": 0.0000 }
{"stock_symbol": "PRF2B", "trade_date": "2015-09-17", "prev_price": 1090.0000, "open_price": 1090.0000, "high_price": 1090.0000, "low_price": 1090.0000, "close_price": 1090.0000, "total_volume": 500, "fb_value": 0, "fs_value": 0, "nfb": 0, "value": 545000, "num_txns": 2, "buy_vol": 0, "bid_qty": 310, "bid_price": 1090.0000, "ask_qty": 715, "ask_price": 1120.0000, "typical_price": 1090.0000, "vwap": 1090.0000, "to_ratio": 0.0000 }
{"stock_symbol": "PRF2B", "trade_date": "2015-09-18", "prev_price": 1090.0000, "open_price": 1090.0000, "high_price": 1090.0000, "low_price": 1080.0000, "close_price": 1080.0000, "total_volume": 1500, "fb_value": 0, "fs_value": 0, "nfb": 0, "value": 1623100, "num_txns": 5, "buy_vol": 0, "bid_qty": 410, "bid_price": 1080.0000, "ask_qty": 715, "ask_price": 1120.0000, "typical_price": 1083.3333, "vwap": 1082.0667, "to_ratio": 0.0000 }
{"stock_symbol": "PRF2B", "trade_date": "2015-09-24", "prev_price": 1080.0000, "open_price": 1100.0000, "high_price": 1100.0000, "low_price": 1100.0000, "close_price": 1100.0000, "total_volume": 2775, "fb_value": 0, "fs_value": 0, "nfb": 0, "value": 3052500, "num_txns": 3, "buy_vol": 2320, "bid_qty": 45, "bid_price": 1100.0000, "ask_qty": 715, "ask_price": 1120.0000, "typical_price": 1100.0000, "vwap": 1100.0000, "to_ratio": 0.0000 }
{"stock_symbol": "PRF2B", "trade_date": "2015-09-28", "prev_price": 1100.0000, "open_price": 1100.0000, "high_price": 1100.0000, "low_price": 1100.0000, "close_price": 1100.0000, "total_volume": 2500, "fb_value": 0, "fs_value": 0, "nfb": 0, "value": 2750000, "num_txns": 6, "buy_vol": 0, "bid_qty": 135, "bid_price": 1100.0000, "ask_qty": 715, "ask_price": 1120.0000, "typical_price": 1100.0000, "vwap": 1100.0000, "to_ratio": 0.0000 }
{"stock_symbol": "PRF2B", "trade_date": "2015-09-30", "prev_price": 1100.0000, "open_price": 1120.0000, "high_price": 1130.0000, "low_price": 1120.0000, "close_price": 1130.0000, "total_volume": 1480, "fb_value": 0, "fs_value": 0, "nfb": 0, "value": 1665250, "num_txns": 6, "buy_vol": 715, "bid_qty": 1935, "bid_price": 1130.0000, "ask_qty": 110, "ask_price": 1140.0000, "typical_price": 1126.6667, "vwap": 1125.1689, "to_ratio": 0.0000 }
{"stock_symbol": "PRF2B", "trade_date": "2015-10-01", "prev_price": 1130.0000, "open_price": 1135.0000, "high_price": 1140.0000, "low_price": 1135.0000, "close_price": 1140.0000, "total_volume": 135, "fb_value": 0, "fs_value": 0, "nfb": 0, "value": 153875, "num_txns": 4, "buy_vol": 135, "bid_qty": 200, "bid_price": 1081.0000, "ask_qty": 480, "ask_price": 1135.0000, "typical_price": 1138.3333, "vwap": 1139.8148, "to_ratio": 0.0000 }
{"stock_symbol": "PRF2B", "trade_date": "2015-10-06", "prev_price": 1140.0000, "open_price": 1141.0000, "high_price": 1141.0000, "low_price": 1140.0000, "close_price": 1140.0000, "total_volume": 750, "fb_value": 0, "fs_value": 0, "nfb": 0, "value": 855500, "num_txns": 2, "buy_vol": 750, "bid_qty": 110, "bid_price": 1090.0000, "ask_qty": 30, "ask_price": 1140.0000, "typical_price": 1140.3333, "vwap": 1140.6667, "to_ratio": 0.0000 }
{"stock_symbol": "PRF2B", "trade_date": "2015-10-09", "prev_price": 1140.0000, "open_price": 1141.0000, "high_price": 1141.0000, "low_price": 1141.0000, "close_price": 1141.0000, "total_volume": 5, "fb_value": 0, "fs_value": 0, "nfb": 0, "value": 5705, "num_txns": 1, "buy_vol": 5, "bid_qty": 145, "bid_price": 1090.0000, "ask_qty": 225, "ask_price": 1141.0000, "typical_price": 1141.0000, "vwap": 1141.0000, "to_ratio": 0.0000 }
{"stock_symbol": "PRF2B", "trade_date": "2015-10-15", "prev_price": 1141.0000, "open_price": 1130.0000, "high_price": 1130.0000, "low_price": 1130.0000, "close_price": 1130.0000, "total_volume": 900, "fb_value": 0, "fs_value": 0, "nfb": 0, "value": 1017000, "num_txns": 1, "buy_vol": 0, "bid_qty": 100, "bid_price": 1036.0000, "ask_qty": 100, "ask_price": 1130.0000, "typical_price": 1130.0000, "vwap": 1130.0000, "to_ratio": 0.0000 }
{"stock_symbol": "PRF2B", "trade_date": "2015-10-16", "prev_price": 1130.0000, "open_price": 1130.0000, "high_price": 1130.0000, "low_price": 1130.0000, "close_price": 1130.0000, "total_volume": 270, "fb_value": 0, "fs_value": 0, "nfb": 0, "value": 305100, "num_txns": 2, "buy_vol": 270, "bid_qty": 150, "bid_price": 1041.0000, "ask_qty": 435, "ask_price": 1130.0000, "typical_price": 1130.0000, "vwap": 1130.0000, "to_ratio": 0.0000 }
{"stock_symbol": "PRF2B", "trade_date": "2015-10-22", "prev_price": 1130.0000, "open_price": 1050.0000, "high_price": 1050.0000, "low_price": 1050.0000, "close_price": 1050.0000, "total_volume": 1920, "fb_value": 0, "fs_value": 0, "nfb": 0, "value": 2016000, "num_txns": 2, "buy_vol": 1920, "bid_qty": 30, "bid_price": 1051.0000, "ask_qty": 500, "ask_price": 1129.0000, "typical_price": 1050.0000, "vwap": 1050.0000, "to_ratio": 0.0000 }
{"stock_symbol": "PRF2B", "trade_date": "2015-10-26", "prev_price": 1050.0000, "open_price": 1052.0000, "high_price": 1052.0000, "low_price": 1052.0000, "close_price": 1052.0000, "total_volume": 100, "fb_value": 0, "fs_value": 0, "nfb": 0, "value": 105200, "num_txns": 2, "buy_vol": 0, "bid_qty": 0, "bid_price": 0.0000, "ask_qty": 0, "ask_price": 0.0000, "typical_price": 1052.0000, "vwap": 1052.0000, "to_ratio": 0.0000 }
{"stock_symbol": "PRF2B", "trade_date": "2015-10-30", "prev_price": 1052.0000, "open_price": 1090.0000, "high_price": 1090.0000, "low_price": 1090.0000, "close_price": 1090.0000, "total_volume": 910, "fb_value": 991900, "fs_value": 0, "nfb": 991900, "value": 991900, "num_txns": 1, "buy_vol": 0, "bid_qty": 0, "bid_price": 0.0000, "ask_qty": 0, "ask_price": 0.0000, "typical_price": 1090.0000, "vwap": 1090.0000, "to_ratio": 0.0000 }
{"stock_symbol": "PRF2B", "trade_date": "2015-11-02", "prev_price": 1090.0000, "open_price": 1089.0000, "high_price": 1089.0000, "low_price": 1089.0000, "close_price": 1089.0000, "total_volume": 10, "fb_value": 10890, "fs_value": 0, "nfb": 10890, "value": 10890, "num_txns": 1, "buy_vol": 10, "bid_qty": 0, "bid_price": 0.0000, "ask_qty": 0, "ask_price": 0.0000, "typical_price": 1089.0000, "vwap": 1089.0000, "to_ratio": 0.0000 }
{"stock_symbol": "PRF2B", "trade_date": "2015-11-03", "prev_price": 1089.0000, "open_price": 1080.0000, "high_price": 1080.0000, "low_price": 1061.0000, "close_price": 1061.0000, "total_volume": 2910, "fb_value": 442800, "fs_value": 0, "nfb": 442800, "value": 3096110, "num_txns": 7, "buy_vol": 0, "bid_qty": 0, "bid_price": 0.0000, "ask_qty": 0, "ask_price": 0.0000, "typical_price": 1067.3333, "vwap": 1063.9553, "to_ratio": 0.0000 }
{"stock_symbol": "PRF2B", "trade_date": "2015-11-09", "prev_price": 1065.0000, "open_price": 1068.0000, "high_price": 1068.0000, "low_price": 1065.0000, "close_price": 1065.0000, "total_volume": 430, "fb_value": 0, "fs_value": 0, "nfb": 0, "value": 458750, "num_txns": 4, "buy_vol": 0, "bid_qty": 0, "bid_price": 0.0000, "ask_qty": 0, "ask_price": 0.0000, "typical_price": 1066.0000, "vwap": 1066.8605, "to_ratio": 0.0000 }
{"stock_symbol": "PRF2B", "trade_date": "2015-11-11", "prev_price": 1065.0000, "open_price": 1099.0000, "high_price": 1129.0000, "low_price": 1098.0000, "close_price": 1129.0000, "total_volume": 455, "fb_value": 0, "fs_value": 0, "nfb": 0, "value": 506445, "num_txns": 6, "buy_vol": 455, "bid_qty": 0, "bid_price": 0.0000, "ask_qty": 0, "ask_price": 0.0000, "typical_price": 1118.6667, "vwap": 1113.0659, "to_ratio": 0.0000 }
{"stock_symbol": "PRF2B", "trade_date": "2015-11-23", "prev_price": 1129.0000, "open_price": 1072.0000, "high_price": 1072.0000, "low_price": 1072.0000, "close_price": 1072.0000, "total_volume": 10, "fb_value": 0, "fs_value": 0, "nfb": 0, "value": 10720, "num_txns": 1, "buy_vol": 0, "bid_qty": 0, "bid_price": 0.0000, "ask_qty": 0, "ask_price": 0.0000, "typical_price": 1072.0000, "vwap": 1072.0000, "to_ratio": 0.0000 }
{"stock_symbol": "PRF2B", "trade_date": "2015-11-25", "prev_price": 1072.0000, "open_price": 1073.0000, "high_price": 1073.0000, "low_price": 1070.0000, "close_price": 1070.0000, "total_volume": 520, "fb_value": 0, "fs_value": 0, "nfb": 0, "value": 556790, "num_txns": 4, "buy_vol": 0, "bid_qty": 0, "bid_price": 0.0000, "ask_qty": 0, "ask_price": 0.0000, "typical_price": 1071.0000, "vwap": 1070.7500, "to_ratio": 0.0000 }
{"stock_symbol": "PRF2B", "trade_date": "2015-11-26", "prev_price": 1070.0000, "open_price": 1073.0000, "high_price": 1073.0000, "low_price": 1070.0000, "close_price": 1072.0000, "total_volume": 1560, "fb_value": 0, "fs_value": 0, "nfb": 0, "value": 1670700, "num_txns": 5, "buy_vol": 0, "bid_qty": 0, "bid_price": 0.0000, "ask_qty": 0, "ask_price": 0.0000, "typical_price": 1071.6667, "vwap": 1070.9615, "to_ratio": 0.0000 }
{"stock_symbol": "PRF2B", "trade_date": "2015-11-27", "prev_price": 1072.0000, "open_price": 1073.0000, "high_price": 1073.0000, "low_price": 1073.0000, "close_price": 1073.0000, "total_volume": 200, "fb_value": 0, "fs_value": 0, "nfb": 0, "value": 214600, "num_txns": 2, "buy_vol": 50, "bid_qty": 0, "bid_price": 0.0000, "ask_qty": 0, "ask_price": 0.0000, "typical_price": 1073.0000, "vwap": 1073.0000, "to_ratio": 0.0000 }
{"stock_symbol": "PRF2B", "trade_date": "2015-12-07", "prev_price": 1073.0000, "open_price": 1073.0000, "high_price": 1073.0000, "low_price": 1072.0000, "close_price": 1072.0000, "total_volume": 260, "fb_value": 0, "fs_value": 0, "nfb": 0, "value": 278920, "num_txns": 2, "buy_vol": 0, "bid_qty": 0, "bid_price": 0.0000, "ask_qty": 0, "ask_price": 0.0000, "typical_price": 1072.3333, "vwap": 1072.7692, "to_ratio": 0.0000 }
{"stock_symbol": "PRF2B", "trade_date": "2015-12-08", "prev_price": 1072.0000, "open_price": 1072.0000, "high_price": 1072.0000, "low_price": 1072.0000, "close_price": 1072.0000, "total_volume": 225, "fb_value": 0, "fs_value": 0, "nfb": 0, "value": 241200, "num_txns": 2, "buy_vol": 0, "bid_qty": 0, "bid_price": 0.0000, "ask_qty": 0, "ask_price": 0.0000, "typical_price": 1072.0000, "vwap": 1072.0000, "to_ratio": 0.0000 }
{"stock_symbol": "PRF2B", "trade_date": "2015-12-09", "prev_price": 1072.0000, "open_price": 1072.0000, "high_price": 1075.0000, "low_price": 1072.0000, "close_price": 1075.0000, "total_volume": 300, "fb_value": 0, "fs_value": 0, "nfb": 0, "value": 321900, "num_txns": 3, "buy_vol": 0, "bid_qty": 0, "bid_price": 0.0000, "ask_qty": 0, "ask_price": 0.0000, "typical_price": 1074.0000, "vwap": 1073.0000, "to_ratio": 0.0000 }
{"stock_symbol": "PRF2B", "trade_date": "2015-12-11", "prev_price": 1075.0000, "open_price": 1075.0000, "high_price": 1075.0000, "low_price": 1075.0000, "close_price": 1075.0000, "total_volume": 140, "fb_value": 0, "fs_value": 0, "nfb": 0, "value": 150500, "num_txns": 2, "buy_vol": 0, "bid_qty": 0, "bid_price": 0.0000, "ask_qty": 0, "ask_price": 0.0000, "typical_price": 1075.0000, "vwap": 1075.0000, "to_ratio": 0.0000 }
{"stock_symbol": "PRF2B", "trade_date": "2015-12-14", "prev_price": 1075.0000, "open_price": 1075.0000, "high_price": 1075.0000, "low_price": 1065.0000, "close_price": 1065.0000, "total_volume": 2870, "fb_value": 0, "fs_value": 0, "nfb": 0, "value": 3073415, "num_txns": 7, "buy_vol": 0, "bid_qty": 0, "bid_price": 0.0000, "ask_qty": 0, "ask_price": 0.0000, "typical_price": 1068.3333, "vwap": 1070.8763, "to_ratio": 0.0000 }
{"stock_symbol": "PRF2B", "trade_date": "2015-12-18", "prev_price": 1065.0000, "open_price": 1067.0000, "high_price": 1067.0000, "low_price": 1065.0000, "close_price": 1065.0000, "total_volume": 500, "fb_value": 0, "fs_value": 0, "nfb": 0, "value": 532920, "num_txns": 4, "buy_vol": 0, "bid_qty": 0, "bid_price": 0.0000, "ask_qty": 0, "ask_price": 0.0000, "typical_price": 1065.6667, "vwap": 1065.8400, "to_ratio": 0.0000 }
{"stock_symbol": "PRF2B", "trade_date": "2015-12-21", "prev_price": 1065.0000, "open_price": 1065.0000, "high_price": 1065.0000, "low_price": 1065.0000, "close_price": 1065.0000, "total_volume": 420, "fb_value": 0, "fs_value": 0, "nfb": 0, "value": 447300, "num_txns": 1, "buy_vol": 0, "bid_qty": 0, "bid_price": 0.0000, "ask_qty": 0, "ask_price": 0.0000, "typical_price": 1065.0000, "vwap": 1065.0000, "to_ratio": 0.0000 }
